opengovcorpus/__init__.py
opengovcorpus/config.py
opengovcorpus/dataset.py
opengovcorpus/embeddings.py
opengovcorpus/exceptions.py
opengovcorpus/models.py
opengovcorpus/py.typed
opengovcorpus/scraper.py
opengovcorpus/utils.py
opengovcorpus/vector_store.py
opengovcorpus-0.1.4.dist-info/licenses/LICENSE
opengovcorpus-0.1.4.dist-info/METADATA
opengovcorpus-0.1.4.dist-info/WHEEL
opengovcorpus-0.1.4.dist-info/top_level.txt
opengovcorpus-0.1.4.dist-info/RECORD
