Metadata-Version: 2.4
Name: opengovcorpus
Version: 0.1.4
Summary: A library for creating structured datasets and RAG embeddings from government websites
Author-email: Prajun Trital <prajuncs@gmail.com>
License: MIT
Project-URL: Homepage, https://github.com/prajun7/open-gov-corpus-py-library
Project-URL: Documentation, https://github.com/prajun7/open-gov-corpus-py-library#readme
Project-URL: Repository, https://github.com/prajun7/open-gov-corpus-py-library
Project-URL: Bug Reports, https://github.com/prajun7/open-gov-corpus-py-library/issues
Keywords: government,scraping,dataset,rag,embeddings,vector-database,nlp,machine-learning,open-data,civic-tech
Classifier: Development Status :: 4 - Beta
Classifier: Intended Audience :: Developers
Classifier: Intended Audience :: Science/Research
Classifier: Topic :: Software Development :: Libraries :: Python Modules
Classifier: Topic :: Scientific/Engineering :: Artificial Intelligence
Classifier: Topic :: Text Processing :: Linguistic
Classifier: License :: OSI Approved :: MIT License
Classifier: Programming Language :: Python :: 3
Classifier: Programming Language :: Python :: 3.8
Classifier: Programming Language :: Python :: 3.9
Classifier: Programming Language :: Python :: 3.10
Classifier: Programming Language :: Python :: 3.11
Classifier: Programming Language :: Python :: 3.12
Classifier: Operating System :: OS Independent
Requires-Python: >=3.8
License-File: LICENSE
Requires-Dist: requests>=2.32
Requires-Dist: beautifulsoup4>=4.14
Requires-Dist: pandas>=2.3
Requires-Dist: openai>=2.7
Requires-Dist: chromadb>=1.3
Requires-Dist: tqdm>=4.67
Requires-Dist: google-generativeai>=0.3.0
Requires-Dist: sentence-transformers>=2.2.0
Dynamic: license-file
